invaro/__init__.py
invaro/accounting/__init__.py
invaro/common/__init__.py
invaro/parser/__init__.py
invaro-0.0.4.dist-info/licenses/LICENSE
invaro-0.0.4.dist-info/METADATA
invaro-0.0.4.dist-info/WHEEL
invaro-0.0.4.dist-info/top_level.txt
invaro-0.0.4.dist-info/RECORD
