Metadata-Version: 2.4
Name: invaro
Version: 0.0.4
Summary: Python SDK for Invaro's document parsing and unified accounting APIs
Author-email: Invaro <support@invaro.ai>
Maintainer-email: Invaro <support@invaro.ai>
License: MIT
Project-URL: Homepage, https://invaro.ai
Project-URL: Documentation, https://docs.invaro.ai
Project-URL: Repository, https://github.com/Invaro/invaro-sdk
Project-URL: Bug Tracker, https://github.com/Invaro/invaro-sdk/issues
Project-URL: Changelog, https://github.com/Invaro/invaro-sdk/blob/main/CHANGELOG.md
Keywords: invaro,document-parsing,accounting,api-client,sdk,invoice-processing,financial-documents
Classifier: Development Status :: 2 - Pre-Alpha
Classifier: Intended Audience :: Developers
Classifier: License :: OSI Approved :: MIT License
Classifier: Operating System :: OS Independent
Classifier: Programming Language :: Python :: 3
Classifier: Programming Language :: Python :: 3.8
Classifier: Programming Language :: Python :: 3.9
Classifier: Programming Language :: Python :: 3.10
Classifier: Programming Language :: Python :: 3.11
Classifier: Programming Language :: Python :: 3.12
Classifier: Topic :: Software Development :: Libraries :: Python Modules
Classifier: Topic :: Office/Business :: Financial
Classifier: Topic :: Text Processing :: General
Requires-Python: >=3.8
License-File: LICENSE
Provides-Extra: dev
Requires-Dist: pytest>=7.0; extra == "dev"
Requires-Dist: pytest-asyncio>=0.21.0; extra == "dev"
Requires-Dist: black>=23.0; extra == "dev"
Requires-Dist: ruff>=0.1.0; extra == "dev"
Requires-Dist: mypy>=1.0; extra == "dev"
Dynamic: license-file
